setup.py
sql_query_dict.py
sql_query_dict.egg-info/PKG-INFO
sql_query_dict.egg-info/SOURCES.txt
sql_query_dict.egg-info/dependency_links.txt
sql_query_dict.egg-info/requires.txt
sql_query_dict.egg-info/top_level.txt