Metadata-Version: 1.0
Name: sql-query-dict
Version: 0.10
Summary: express sql queries as python dictionaries
Home-page: http://github.com/PlotWatt/sql_query_dict
Author: PlotWatt
Author-email: zdwiel@plotwatt.com
License: Apache
Platform: UNKNOWN
